pusoft/__init__.py
pusoft/home_page.py
pusoft/pusoft_package_manager.py
pusoft-0.1.1.dist-info/LICENSE
pusoft-0.1.1.dist-info/METADATA
pusoft-0.1.1.dist-info/WHEEL
pusoft-0.1.1.dist-info/entry_points.txt
pusoft-0.1.1.dist-info/top_level.txt
pusoft-0.1.1.dist-info/RECORD
