Metadata-Version: 2.1
Name: pusoft
Version: 0.1.1
Summary: PUSoft Tools
Home-page: https://github.com/pumkin1001/pusoft
Author: Pumpkin_1001
Author-email: 2752349525@qq.com
License: UNKNOWN
Platform: UNKNOWN
Requires-Dist: colorama
